tezzautoml/__init__.py
tezzautoml/automl.py
tezzautoml/main.py
tezzautoml/models.py
TezzAutoML-0.1.5.dist-info/LICENSE
TezzAutoML-0.1.5.dist-info/METADATA
TezzAutoML-0.1.5.dist-info/WHEEL
TezzAutoML-0.1.5.dist-info/top_level.txt
TezzAutoML-0.1.5.dist-info/RECORD
