Metadata-Version: 2.1
Name: TezzAutoML
Version: 0.1.5
Summary: Just another AutoML library, but better and faster.
Home-page: https://github.com/Japkeerat/TezzAutoML
Author: Japkeerat Singh
Author-email: japkeerat21@gmail.com
License: CC0-1.0
Keywords: automl machine-learning ml data-science
Classifier: Development Status :: 3 - Alpha
Classifier: Intended Audience :: Developers
Classifier: Topic :: Scientific/Engineering :: Artificial Intelligence
Classifier: Topic :: Software Development :: Libraries
Classifier: Topic :: Software Development :: Libraries :: Python Modules
Classifier: License :: CC0 1.0 Universal (CC0 1.0) Public Domain Dedication
Classifier: Programming Language :: Python :: 3.11
Requires-Python: >=3.11
License-File: LICENSE
Requires-Dist: pandas ==2.1.2
Requires-Dist: optuna ==3.4.0
Requires-Dist: xgboost ==2.0.1
Requires-Dist: scikit-learn ==1.3.2
Requires-Dist: mlflow ==2.8.0
Requires-Dist: lightgbm ==3.3.5
